existrike/__init__.py
existrike/main.py
existrike/accounts/accounts.db
existrike/auxiliaries/403-bypass/403.py
existrike/auxiliaries/403-bypass/config.cfg
existrike/auxiliaries/403-bypass/run.sh
existrike/auxiliaries/adminpage/bruteforce/config.cfg
existrike/auxiliaries/adminpage/bruteforce/fuzz.py
existrike/auxiliaries/adminpage/bruteforce/run.sh
existrike/auxiliaries/adminpage/bruteforce/wordlist.txt
existrike/auxiliaries/apache/finder/bruteforce/config.cfg
existrike/auxiliaries/apache/finder/bruteforce/fuzz.py
existrike/auxiliaries/apache/finder/bruteforce/run.sh
existrike/auxiliaries/apache/finder/bruteforce/wordlist.txt
existrike/auxiliaries/fuzzing/finder/dirs/config.cfg
existrike/auxiliaries/fuzzing/finder/dirs/fuzz.py
existrike/auxiliaries/fuzzing/finder/dirs/run.sh
existrike/auxiliaries/fuzzing/finder/dirs/wordlist.txt
existrike/auxiliaries/joomla/finder/dirs/config.cfg
existrike/auxiliaries/joomla/finder/dirs/fuzz.py
existrike/auxiliaries/joomla/finder/dirs/run.sh
existrike/auxiliaries/joomla/finder/dirs/wordlist.txt
existrike/auxiliaries/md5decrypt/bruteforce/config.cfg
existrike/auxiliaries/md5decrypt/bruteforce/md5.py
existrike/auxiliaries/md5decrypt/bruteforce/medium.txt
existrike/auxiliaries/md5decrypt/bruteforce/run.sh
existrike/auxiliaries/md5decrypt/bruteforce/small.txt
existrike/auxiliaries/md5decrypt/bruteforce/w.txt
existrike/auxiliaries/paramfinder/403.py
existrike/auxiliaries/paramfinder/config.cfg
existrike/auxiliaries/paramfinder/run.sh
existrike/auxiliaries/wordlist/gen/admin/admin.py
existrike/auxiliaries/wordlist/gen/admin/config.cfg
existrike/auxiliaries/wordlist/gen/admin/run.sh
existrike/exploits/CVE-2024-38856/config.cfg
existrike/exploits/CVE-2024-38856/exploit.py
existrike/exploits/CVE-2024-38856/run.sh
existrike/exploits/CVE-2024-38856/use.txt
existrike/exploits/expiravitpmc/interpreter/config.cfg
existrike/exploits/expiravitpmc/interpreter/interpreter.py
existrike/exploits/expiravitpmc/interpreter/run.sh
existrike-0.1.3.dist-info/METADATA
existrike-0.1.3.dist-info/WHEEL
existrike-0.1.3.dist-info/entry_points.txt
existrike-0.1.3.dist-info/top_level.txt
existrike-0.1.3.dist-info/RECORD
