Metadata-Version: 2.1
Name: existrike
Version: 0.1.3
Summary: Framework for pentesting
Author: RADNET64
Author-email: radnet@tutamail.com
License: MIT
Requires-Dist: requests
Requires-Dist: aiohttp
Requires-Dist: colorama
Requires-Dist: tqdm
